{
	"minecraft:stonecutter":
	{
		"crafting": 10
	},
	"minecraft:smoker":
	{
		"crafting": 10
	},
	"minecraft:blast_furnace":
	{
		"crafting": 10
	},
	"ironchest:iron_to_gold_chest_upgrade":
	{
		"smithing": 30
	},
	"ironchest:gold_to_diamond_chest_upgrade":
	{
		"smithing": 40
	},
	"ironchest:copper_to_silver_chest_upgrade":
	{
		"smithing": 20
	},
	"ironchest:silver_to_gold_chest_upgrade":
	{
		"smithing": 30
	},
	"ironchest:copper_to_iron_chest_upgrade":
	{
		"smithing": 20
	},
	"ironchest:diamond_to_crystal_chest_upgrade":
	{
		"smithing": 50
	},
	"ironchest:wood_to_iron_chest_upgrade":
	{
		"smithing": 20
	},
	"ironchest:wood_to_copper_chest_upgrade":
	{
		"smithing": 10
	},
	"ironchest:diamond_to_obsidian_chest_upgrade":
	{
		"smithing": 50
	},
	"ironchest:iron_chest":
	{
		"smithing": 20
	},
	"ironchest:gold_chest":
	{
		"smithing": 30
	},
	"ironchest:diamond_chest":
	{
		"smithing": 40
	},
	"ironchest:copper_chest":
	{
		"smithing": 10
	},
	"ironchest:silver_chest":
	{
		"smithing": 20
	},
	"ironchest:crystal_chest":
	{
		"smithing": 50
	},
	"ironchest:obsidian_chest":
	{
		"smithing": 50
	},
	"storagedrawers:controller":
	{
		"crafting": 40
	},
	"storagedrawers:controller_slave":
	{
		"crafting": 50
	},
	"storagedrawers:compacting_drawers_3":
	{
		"crafting": 30
	},
	"storagedrawers:obsidian_storage_upgrade":
	{
		"crafting": 10
	},
	"storagedrawers:iron_storage_upgrade":
	{
		"crafting": 20
	},
	"storagedrawers:gold_storage_upgrade":
	{
		"crafting": 30
	},
	"storagedrawers:diamond_storage_upgrade":
	{
		"crafting": 40
	},
	"storagedrawers:emerald_storage_upgrade":
	{
		"crafting": 50
	},
	"storagedrawers:void_upgrade":
	{
		"crafting": 20
	},
	"storagedrawers:conversion_upgrade":
	{
		"crafting": 25
	},
	"storagedrawers:illumination_upgrade":
	{
		"crafting": 25
	}
}